{
  "world": {
    "top100": {
      "name": "Top World",
      "tracks": 100,
      "fans": "868.544",
      "image": "https://e-cdns-images.dzcdn.net/images/playlist/0b92c2f9e94a1a3650f0de769c4fc07c/264x264-000000-80-0-0.jpg"
    }
  },
  "brazil": {
    "top100": {
      "name": "Top Brasil",
      "tracks": 100,
      "fans": "5.782.600",
      "image": "https://e-cdns-images.dzcdn.net/images/playlist/cec8c04c6e10f69af2702dc1c89b5366/278x278-000000-80-0-0.jpg"
    }
  },
  "usa": {
    "top100": {
      "name": "Top USA",
      "tracks": 100,
      "fans": "868.544",
      "image": "https://e-cdns-images.dzcdn.net/images/playlist/cec8c04c6e10f69af2702dc1c89b5366/278x278-000000-80-0-0.jpg"
    }
  },
  "uk": {
    "top100": {
      "name": "Top UK",
      "tracks": 100,
      "fans": "5.782.600",
      "image": "https://e-cdns-images.dzcdn.net/images/playlist/cec8c04c6e10f69af2702dc1c89b5366/278x278-000000-80-0-0.jpg"
    }
  },
  "germany": {
    "top100": {
      "name": "Top Germany",
      "tracks": 100,
      "fans": "868.544",
      "image": "https://e-cdns-images.dzcdn.net/images/playlist/cec8c04c6e10f69af2702dc1c89b5366/278x278-000000-80-0-0.jpg"
    }
  },
  "france": {
    "top100": {
      "name": "Top France",
      "tracks": 100,
      "fans": "5.782.600",
      "image": "https://e-cdns-images.dzcdn.net/images/playlist/cec8c04c6e10f69af2702dc1c89b5366/278x278-000000-80-0-0.jpg"
    }
  },
  "colombia": {
    "top100": {
      "name": "Top Colombia",
      "tracks": 100,
      "fans": "868.544",
      "image": "https://e-cdns-images.dzcdn.net/images/playlist/cec8c04c6e10f69af2702dc1c89b5366/278x278-000000-80-0-0.jpg"
    }
  },
  "canada": {
    "top100": {
      "name": "Top Canada",
      "tracks": 100,
      "fans": "5.782.600",
      "image": "https://e-cdns-images.dzcdn.net/images/playlist/cec8c04c6e10f69af2702dc1c89b5366/278x278-000000-80-0-0.jpg"
    }
  },
  "mexico": {
    "top100": {
      "name": "Top Mexico",
      "tracks": 100,
      "fans": "5.782.600",
      "image": "https://e-cdns-images.dzcdn.net/images/playlist/cec8c04c6e10f69af2702dc1c89b5366/278x278-000000-80-0-0.jpg"
    }
  },
  "venezuela": {
    "top100": {
      "name": "Top Venezuela",
      "tracks": 100,
      "fans": "5.782.600",
      "image": "https://e-cdns-images.dzcdn.net/images/playlist/cec8c04c6e10f69af2702dc1c89b5366/278x278-000000-80-0-0.jpg"
    }
  },
  "mostSearched": [
    {
      "tag": "top-brazil",
      "h2": "Os hits de hoje"
    }
  ],
  "popular": {
    "musics": [
      {
        "tag": "top-brazil",
        "h2": "Os hits de hoje"
      }
    ],
    "playlists": [
      {
        "tag": "top-brazil",
        "h2": "Os hits de hoje"
      }
    ],
    "albums": [
      {
        "tag": "top-brazil",
        "h2": "Os hits de hoje"
      }
    ],
    "artists": [
      {
        "tag": "top-brazil",
        "h2": "Os hits de hoje"
      }
    ]
  }
}
